{
  "name": "第二关 - 洗衣房奇遇",
  "startRoom": 0,
  "description": [
    "（晚上九点，洗衣房）",
    "（智科er端着一盆脏衣服走进来）",
    "「智科er」 \n（看着盆里堆积如山的袜子和内裤）",
    "「智科er」 \n 这些脏衣服已经放了一周了...再不洗就要成精了。",
    "【公告栏】\n「请勿在公共洗衣机清洗袜子和内衣」",
    "「智科er」 \n ...",
    "「智科er」 \n（看看公告栏，又看看手里的袜子）",
    "「智科er」 \n 我不管了！大不了手洗！",
    "（认命地拿出洗衣盆，打开水龙头）",
    "「智科er」 \n（冰冷的水流浇在手上）嘶啊啊啊啊！好冰！",
    "（一边搓袜子一边小声抱怨）",
    "「智科er」 \n 这些袜子怎么这么臭...是谁的袜子...",
    "「智科er」 \n 哦，是我的。",
    "（突然，洗衣房的灯开始闪烁）",
    "「智科er」 \n 嗯？怎么回事？",
    "（一只袜子从盆里飘了起来）",
    "「智科er」 \n ？？？",
    "（更多的袜子、内裤开始蠕蠕欲动）",
    "「智科er」 \n 等等等等！你们这是干什么！",
    "【臭袜子】\n「我们受够了！一周不洗我们，现在又想把我们扔进冰冷的水里！」",
    "「智科er」 \n 什么情况？？脏衣服成精了？？",
    "（臭袜子们朝智科er扑过来）",
    "「智科er」 \n 啥啊啊啊啊啊！"
  ],
  "rooms": [
    {
      "id": 0,
      "name": "Room 1 - Initial",
      "background": "map2",
      "enemies": [],
      "hasBoss": false,
      "hasChest": true,
      "isChestLocked": false,
      "doors": {
        "up": 4,
        "down": 2,
        "left": 1,
        "right": -1
      }
    },
    {
      "id": 1,
      "name": "Room 2 - Combat",
      "background": "map2",
      "enemies": [
        {
          "type": "sock_normal",
          "count": 3
        },
        {
          "type": "sock_shooter",
          "count": 3
        }
      ],
      "hasBoss": false,
      "hasChest": false,
      "isChestLocked": false,
      "doors": {
        "up": -1,
        "down": -1,
        "left": -1,
        "right": 0
      }
    },
    {
      "id": 2,
      "name": "Room 3 - Special",
      "background": "map2",
      "enemies": [],
      "hasBoss": false,
      "hasChest": true,
      "isChestLocked": false,
      "doors": {
        "up": 0,
        "down": -1,
        "left": -1,
        "right": -1
      }
    },
    {
      "id": 3,
      "name": "Room 4 - Combat",
      "background": "map2",
      "enemies": [
        {
          "type": "walker",
          "count": 3
        },
        {
          "type": "pants",
          "count": 3
        }
      ],
      "hasBoss": false,
      "hasChest": false,
      "isChestLocked": false,
      "doors": {
        "up": -1,
        "down": -1,
        "left": 5,
        "right": 7
      }
    },
    {
      "id": 4,
      "name": "Room 5 - Combat",
      "background": "map2",
      "enemies": [
        {
          "type": "sock_shooter",
          "count": 6
        },
        {
          "type": "sock_angrily",
          "count": 1
        },
        {
          "type": "sock_normal",
          "count": 2
        }
      ],
      "hasBoss": false,
      "hasChest": false,
      "isChestLocked": false,
      "doors": {
        "up": 5,
        "down": 0,
        "left": -1,
        "right": 8
      }
    },
    {
      "id": 5,
      "name": "Room 6 - Combat",
      "background": "map2",
      "enemies": [
        {
          "type": "sock_shooter",
          "count": 3
        },
        {
          "type": "pants",
          "count": 1
        },
        {
          "type": "sock_angrily",
          "count": 3
        }
      ],
      "hasBoss": false,
      "hasChest": false,
      "isChestLocked": false,
      "doors": {
        "up": 9,
        "down": 4,
        "left": 6,
        "right": 3
      }
    },
    {
      "id": 6,
      "name": "Room 7 - Item",
      "background": "map2",
      "enemies": [],
      "hasBoss": false,
      "hasChest": true,
      "isChestLocked": false,
      "doors": {
        "up": -1,
        "down": -1,
        "left": -1,
        "right": 5
      }
    },
    {
      "id": 7,
      "name": "Room 8 - Item",
      "background": "map2",
      "enemies": [],
      "hasBoss": false,
      "hasChest": true,
      "isChestLocked": true,
      "doors": {
        "up": -1,
        "down": -1,
        "left": 3,
        "right": -1
      }
    },
    {
      "id": 8,
      "name": "Room 9 - Special",
      "background": "map2",
      "enemies": [],
      "hasBoss": false,
      "hasChest": true,
      "isChestLocked": false,
      "doors": {
        "up": -1,
        "down": -1,
        "left": 4,
        "right": -1
      }
    },
    {
      "id": 9,
      "name": "Room 10 - Special (Boss)",
      "background": "map2",
      "enemies": [
        {
          "type": "sock_normal",
          "count": 2
        },
        {
          "type": "sock_angrily",
          "count": 1
        },
        {
          "type": "walker",
          "count": 1
        },
        {
          "type": "sock_shooter",
          "count": 2
        },
        {
          "type": "pants",
          "count": 1
        }
      ],
      "hasBoss": true,
      "bossDialog": [
        "（洗衣房的灯光闪烁着，空气中弥漫着一股异样的气息）",
        "【洗衣机】\n『你好呀！欢迎来到洗衣房～』",
        "【洗衣机】\n『我可以帮你洗衣服哦，把脏衣服放进来吧！咕噜咕噜～』",
        "（旁白）\n（这台洗衣机...好像有什么不对劲）",
        "（旁白）\n（仔细一看，滚筒里翻滚着无数臭袜子和内裤...散发着诡异的气息）",
        "（旁白）\n「这台洗衣机已被臭袜子和内裤污染，它正处于巨大的痛苦之中！」",
        "（旁白）\n「唯一解救它的办法...就是打败它，让它恢复清醒！」",
        "「智科er」 \n 我明白了！我会帮助你的！",
        "【洗衣机】\n『什...什么？你说什么？我很好啊...咕噜咕噜～』",
        "【洗衣机】\n『不要靠近我！我要开始甩干模式了！』",
        "（战斗开始！）"
      ],
      "bossDialogBackground": "assets/boss_dia/boss2_1.png",
      "usagiChestItems": [
        "black_heart",
        "blood_bag",
        "fire_rate_boost",
        "damage_boost"
      ],
      "hasChest": true,
      "isChestLocked": false,
      "doors": {
        "up": -1,
        "down": 5,
        "left": -1,
        "right": -1
      }
    }
  ]
}